siate/__init__.py
siate/allin.py
siate/assets_liquidity.py
siate/assets_liquidity_test.py
siate/beta_adjustment.py
siate/beta_adjustment_test.py
siate/blockchain.py
siate/bond.py
siate/bond_base.py
siate/bond_test.py
siate/capm_beta.py
siate/capm_beta_test.py
siate/common.py
siate/copyrights.py
siate/cryptocurrency.py
siate/cryptocurrency_test.py
siate/economy.py
siate/economy_test.py
siate/esg.py
siate/esg_test.py
siate/fama_french.py
siate/fama_french_test.py
siate/financial_base.py
siate/financial_statements.py
siate/financial_statements_test.py
siate/financials.py
siate/financials_test.py
siate/fund_china.py
siate/fund_china_test.py
siate/grafix.py
siate/grafix_test.py
siate/holding_risk.py
siate/markowitz.py
siate/markowitz_test.py
siate/option_pricing.py
siate/option_pricing_test.py
siate/risk_adjusted_return.py
siate/risk_adjusted_return_test.py
siate/risk_evaluation.py
siate/risk_evaluation_test.py
siate/risk_free_rate.py
siate/risk_free_rate_test.py
siate/sector_china.py
siate/sector_china_test.py
siate/security_prices.py
siate/security_prices_test.py
siate/stock.py
siate/stock_base.py
siate/stock_china.py
siate/stock_china_20210514.py
siate/stock_china_test.py
siate/stock_test.py
siate/transaction.py
siate/transaction_test.py
siate/translate.py
siate/universal_test.py
siate/var_model_validation.py
siate-1.2.1.20.dist-info/METADATA
siate-1.2.1.20.dist-info/WHEEL
siate-1.2.1.20.dist-info/top_level.txt
siate-1.2.1.20.dist-info/zip-safe
siate-1.2.1.20.dist-info/RECORD
